sans_db/__init__.py
sans_db/context_managers.py
sans_db/exceptions.py
sans_db/template_backends/__init__.py
sans_db/template_backends/django_sans_db.py
sans_db/templatetags/__init__.py
sans_db/templatetags/sansdb.py
django_sans_db-1.2.0.dist-info/LICENSE
django_sans_db-1.2.0.dist-info/WHEEL
django_sans_db-1.2.0.dist-info/METADATA
django_sans_db-1.2.0.dist-info/RECORD
